orbis_eval/__init__.py
orbis_eval/__version__.py
orbis_eval/main.py
orbis_eval/config/__init__.py
orbis_eval/config/paths.py
orbis_eval/core/__init__.py
orbis_eval/core/base.py
orbis_eval/core/orbis_app.py
orbis_eval/core/orbis_setup.py
orbis_eval/core/pipeline.py
orbis_eval/core/rucksack.py
orbis_eval/data/orbis_config/settings.json
orbis_eval/data/tests/corpora/harvest/source.txt
orbis_eval/data/tests/corpora/harvest/computed/weblyzard_harvest/33a87173ec924437f2546e6b403421bf.json
orbis_eval/data/tests/corpora/harvest/corpus/33a87173ec924437f2546e6b403421bf-modified.txt
orbis_eval/data/tests/corpora/harvest/corpus/33a87173ec924437f2546e6b403421bf.txt
orbis_eval/data/tests/corpora/harvest/gold/harvest.gs
orbis_eval/data/tests/corpora/harvest/source/forum.utorrent.com.topic.23012-check-on-startup..json
orbis_eval/data/tests/corpora/rss1/source.txt
orbis_eval/data/tests/corpora/rss1/computed/aida/0.json
orbis_eval/data/tests/corpora/rss1/computed/babelfly/0.json
orbis_eval/data/tests/corpora/rss1/computed/recognize/0.json
orbis_eval/data/tests/corpora/rss1/computed/spotlight/0.json
orbis_eval/data/tests/corpora/rss1/corpus/0.txt
orbis_eval/data/tests/corpora/rss1/gold/rss1.gs
orbis_eval/data/tests/queue/harvest_weblyzard_harvest_local.yaml
orbis_eval/data/tests/queue/rss1_aida_local.yaml
orbis_eval/data/tests/queue/rss1_aida_web.yaml
orbis_eval/data/tests/queue/rss1_babelfly_local.yaml
orbis_eval/data/tests/queue/rss1_babelfly_web.yaml
orbis_eval/data/tests/queue/rss1_spotlight_local.yaml
orbis_eval/data/tests/queue/rss1_spotlight_web.yaml
orbis_eval/interfaces/__init__.py
orbis_eval/interfaces/addons/__init__.py
orbis_eval/interfaces/addons/main.py
orbis_eval/libs/__init__.py
orbis_eval/libs/addons.py
orbis_eval/libs/arguments.py
orbis_eval/libs/calculate_position.py
orbis_eval/libs/cli.py
orbis_eval/libs/config.py
orbis_eval/libs/decorators.py
orbis_eval/libs/files.py
orbis_eval/libs/filter.py
orbis_eval/libs/interfaces.py
orbis_eval/libs/logger.py
orbis_eval-2.3.5.dist-info/LICENSE
orbis_eval-2.3.5.dist-info/METADATA
orbis_eval-2.3.5.dist-info/WHEEL
orbis_eval-2.3.5.dist-info/entry_points.txt
orbis_eval-2.3.5.dist-info/top_level.txt
orbis_eval-2.3.5.dist-info/RECORD
