Metadata-Version: 2.1
Name: orbis-eval
Version: 2.3.5
Summary: An Extendable Evaluation Pipeline for Named Entity Drill-Down Analysis
Home-page: https://github.com/orbis-eval/orbis_eval
Author: fabod, rogerwaldvogel
License: GPL2
Platform: UNKNOWN
Requires-Python: >3.6
Requires-Dist: SPARQLWrapper (==1.8.2)
Requires-Dist: coloredlogs (>=10.0)
Requires-Dist: fuzzysearch
Requires-Dist: mdutils
Requires-Dist: pyyaml (>=4.2b1)
Provides-Extra: aggregation_aida
Requires-Dist: orbis-plugin-aggregation-aida ; extra == 'aggregation_aida'
Provides-Extra: aggregation_babelfly
Requires-Dist: orbis-plugin-aggregation-babelfly ; extra == 'aggregation_babelfly'
Provides-Extra: aggregation_local_cache
Requires-Dist: orbis-plugin-aggregation-local-cache ; extra == 'aggregation_local_cache'
Provides-Extra: aggregation_recognize
Requires-Dist: orbis-plugin-aggregation-recognize ; extra == 'aggregation_recognize'
Provides-Extra: aggregation_spotlight
Requires-Dist: orbis-plugin-aggregation-spotlight ; extra == 'aggregation_spotlight'
Provides-Extra: aggregation_weblyzard_harvest
Requires-Dist: orbis-plugin-aggregation-weblyzard-harvest ; extra == 'aggregation_weblyzard_harvest'
Provides-Extra: all
Requires-Dist: orbis-addon-repoman ; extra == 'all'
Requires-Dist: orbis-plugin-aggregation-aida ; extra == 'all'
Requires-Dist: orbis-plugin-aggregation-babelfly ; extra == 'all'
Requires-Dist: orbis-plugin-aggregation-local-cache ; extra == 'all'
Requires-Dist: orbis-plugin-aggregation-recognize ; extra == 'all'
Requires-Dist: orbis-plugin-aggregation-spotlight ; extra == 'all'
Requires-Dist: orbis-plugin-aggregation-weblyzard-harvest ; extra == 'all'
Requires-Dist: orbis-plugin-evaluation-binary-classification-evaluation ; extra == 'all'
Requires-Dist: orbis-plugin-metrics-binary-classification-metrics ; extra == 'all'
Requires-Dist: orbis-plugin-scoring-nel-scorer ; extra == 'all'
Requires-Dist: orbis-plugin-scoring-ner-scorer ; extra == 'all'
Requires-Dist: orbis-plugin-scoring-wl-harvest-scorer ; extra == 'all'
Requires-Dist: orbis-plugin-storage-cache-webservice-results ; extra == 'all'
Requires-Dist: orbis-plugin-storage-csv-result-list ; extra == 'all'
Requires-Dist: orbis-plugin-storage-html-pages ; extra == 'all'
Provides-Extra: all_addons
Requires-Dist: orbis-addon-repoman ; extra == 'all_addons'
Provides-Extra: all_aggregations
Requires-Dist: orbis-plugin-aggregation-aida ; extra == 'all_aggregations'
Requires-Dist: orbis-plugin-aggregation-babelfly ; extra == 'all_aggregations'
Requires-Dist: orbis-plugin-aggregation-local-cache ; extra == 'all_aggregations'
Requires-Dist: orbis-plugin-aggregation-recognize ; extra == 'all_aggregations'
Requires-Dist: orbis-plugin-aggregation-spotlight ; extra == 'all_aggregations'
Requires-Dist: orbis-plugin-aggregation-weblyzard-harvest ; extra == 'all_aggregations'
Provides-Extra: all_evaluations
Requires-Dist: orbis-plugin-evaluation-binary-classification-evaluation ; extra == 'all_evaluations'
Provides-Extra: all_metricss
Requires-Dist: orbis-plugin-metrics-binary-classification-metrics ; extra == 'all_metricss'
Provides-Extra: all_plugins
Requires-Dist: orbis-plugin-aggregation-aida ; extra == 'all_plugins'
Requires-Dist: orbis-plugin-aggregation-babelfly ; extra == 'all_plugins'
Requires-Dist: orbis-plugin-aggregation-local-cache ; extra == 'all_plugins'
Requires-Dist: orbis-plugin-aggregation-recognize ; extra == 'all_plugins'
Requires-Dist: orbis-plugin-aggregation-spotlight ; extra == 'all_plugins'
Requires-Dist: orbis-plugin-aggregation-weblyzard-harvest ; extra == 'all_plugins'
Requires-Dist: orbis-plugin-evaluation-binary-classification-evaluation ; extra == 'all_plugins'
Requires-Dist: orbis-plugin-metrics-binary-classification-metrics ; extra == 'all_plugins'
Requires-Dist: orbis-plugin-scoring-nel-scorer ; extra == 'all_plugins'
Requires-Dist: orbis-plugin-scoring-ner-scorer ; extra == 'all_plugins'
Requires-Dist: orbis-plugin-scoring-wl-harvest-scorer ; extra == 'all_plugins'
Requires-Dist: orbis-plugin-storage-cache-webservice-results ; extra == 'all_plugins'
Requires-Dist: orbis-plugin-storage-csv-result-list ; extra == 'all_plugins'
Requires-Dist: orbis-plugin-storage-html-pages ; extra == 'all_plugins'
Provides-Extra: all_scorings
Requires-Dist: orbis-plugin-scoring-nel-scorer ; extra == 'all_scorings'
Requires-Dist: orbis-plugin-scoring-ner-scorer ; extra == 'all_scorings'
Requires-Dist: orbis-plugin-scoring-wl-harvest-scorer ; extra == 'all_scorings'
Provides-Extra: all_storages
Requires-Dist: orbis-plugin-storage-cache-webservice-results ; extra == 'all_storages'
Requires-Dist: orbis-plugin-storage-csv-result-list ; extra == 'all_storages'
Requires-Dist: orbis-plugin-storage-html-pages ; extra == 'all_storages'
Provides-Extra: evaluation_binary_classification_evaluation
Requires-Dist: orbis-plugin-evaluation-binary-classification-evaluation ; extra == 'evaluation_binary_classification_evaluation'
Provides-Extra: metrics_binary_classification_metrics
Requires-Dist: orbis-plugin-metrics-binary-classification-metrics ; extra == 'metrics_binary_classification_metrics'
Provides-Extra: repoman
Requires-Dist: orbis-addon-repoman ; extra == 'repoman'
Provides-Extra: scoring_nel_scorer
Requires-Dist: orbis-plugin-scoring-nel-scorer ; extra == 'scoring_nel_scorer'
Provides-Extra: scoring_ner_scorer
Requires-Dist: orbis-plugin-scoring-ner-scorer ; extra == 'scoring_ner_scorer'
Provides-Extra: scoring_wl_harvest_scorer
Requires-Dist: orbis-plugin-scoring-wl-harvest-scorer ; extra == 'scoring_wl_harvest_scorer'
Provides-Extra: storage_cache_webservice_results
Requires-Dist: orbis-plugin-storage-cache-webservice-results ; extra == 'storage_cache_webservice_results'
Provides-Extra: storage_csv_result_list
Requires-Dist: orbis-plugin-storage-csv-result-list ; extra == 'storage_csv_result_list'
Provides-Extra: storage_html_pages
Requires-Dist: orbis-plugin-storage-html-pages ; extra == 'storage_html_pages'
